[{"BankId":18,"BankType":3,"ChineseName":"汇丰银行","EnglishName":"","Sort":18},{"BankId":40,"BankType":3,"ChineseName":"花旗银行","EnglishName":"","Sort":40},{"BankId":41,"BankType":3,"ChineseName":"恒生银行","EnglishName":"","Sort":41},{"BankId":42,"BankType":3,"ChineseName":"渣打银行","EnglishName":"","Sort":42},{"BankId":43,"BankType":3,"ChineseName":"东亚银行","EnglishName":"","Sort":43},{"BankId":44,"BankType":3,"ChineseName":"德意志银行","EnglishName":"","Sort":44},{"BankId":45,"BankType":3,"ChineseName":"瑞士银行","EnglishName":"","Sort":45},{"BankId":46,"BankType":3,"ChineseName":"荷兰银行","EnglishName":"","Sort":46}]